DataStruct_Kit/__init__.py
DataStruct_Kit/hashtables.py
DataStruct_Kit/performance.py
DataStruct_Kit/searching.py
DataStruct_Kit/sorting.py
DataStruct_Kit/utils.py
DataStruct_Kit/graphs/__init__.py
DataStruct_Kit/graphs/algorithms.py
DataStruct_Kit/graphs/directed_graph.py
DataStruct_Kit/graphs/graph.py
DataStruct_Kit/trees/__init__.py
DataStruct_Kit/trees/avl_tree.py
DataStruct_Kit/trees/binary_tree.py
DataStruct_Kit/trees/heap.py
datastruct_kit-0.1.2.dist-info/licenses/LICENSE
datastruct_kit-0.1.2.dist-info/METADATA
datastruct_kit-0.1.2.dist-info/WHEEL
datastruct_kit-0.1.2.dist-info/top_level.txt
datastruct_kit-0.1.2.dist-info/RECORD
