Metadata-Version: 2.4
Name: DataStruct_Kit
Version: 0.1.2
Summary: Python package implementing essential data structures and algorithms
Author-email: RANGDAL PAVANSAI <pavansai.20066@gmail.com>
License: MIT
Project-URL: Homepage, https://github.com/Pavansai20054/DataStruct_Kit
Project-URL: Documentation, https://github.com/Pavansai20054/DataStruct_Kit#readme
Classifier: Programming Language :: Python :: 3
Classifier: License :: OSI Approved :: MIT License
Classifier: Operating System :: OS Independent
Requires-Python: >=3.8
License-File: LICENSE
Dynamic: license-file
